tushare_crawler/__init__.py
tushare_crawler-0.1.0.dist-info/METADATA
tushare_crawler-0.1.0.dist-info/WHEEL
tushare_crawler-0.1.0.dist-info/RECORD
